{
    "assets": [
        {
            "left": 270,
            "top": 50,
            "width": 540,
            "height": 405,
            "asset_uri": "mucho_mambo_logo.png"
        },
        {
            "left": 784,
            "top": 880,
            "width": 270,
            "height": 122,
            "asset_uri": "buffalo_wild_wings_logo.png"
        },
        {
            "left": 25,
            "top": 880,
            "width": 270,
            "height": 75,
            "asset_uri": "palladium_dance_company_logo.png"
        }
    ],
    "texts": [
        {
            "center_x": 540,
            "center_y": 540,
            "font_size": 20,
            "font_family": "amatic sc",
            "content": "Thursday 9PM to 12AM"
        }
    ],
    "poster_image": {
        "x": 0,
        "y": 0,
        "width": 1080,
        "height": 1080,
        "url": "https://cdn.discordapp.com/attachments/1224586563510468619/1233344295852048446/gd_superagi_98661_Create_a_poster_Golden_starry_theme_backgroun_231ee637-294b-4df1-8379-cf854125208a.png?ex=662cc0e2&is=662b6f62&hm=041109bf390b224d8c8633d83e555f4a0c1e82202ff45fc7b123c045b669d3b0&"
    }
}